rcps/__init__.py
rcps/main.py
rcps/assets/favicon.ico
rcps/assets/logo.png
rcps/assets/temp.png
rcps/utils/__constant.py
rcps/utils/__init__.py
rcps/utils/__key_maps.py
rcps/utils/base.py
rcps/utils/gui.py
rcps/utils/utils.py
rcps-0.0.4.dist-info/LICENSE
rcps-0.0.4.dist-info/METADATA
rcps-0.0.4.dist-info/WHEEL
rcps-0.0.4.dist-info/entry_points.txt
rcps-0.0.4.dist-info/top_level.txt
rcps-0.0.4.dist-info/RECORD
