Metadata-Version: 2.2
Name: rcps
Version: 0.0.4
Summary: A tool to control a target pc remotely with a bunch of other tools.
Author: arpy8
Classifier: Programming Language :: Python :: 3
Classifier: License :: OSI Approved :: MIT License
Classifier: Operating System :: OS Independent
License-File: LICENSE
Requires-Dist: wheel
Requires-Dist: termcolor
Requires-Dist: setuptools
Requires-Dist: argparse
Requires-Dist: argparse
Requires-Dist: pynput
Requires-Dist: opencv-python
Requires-Dist: pyautogui
Requires-Dist: customtkinter
Dynamic: author
Dynamic: classifier
Dynamic: description
Dynamic: description-content-type
Dynamic: requires-dist
Dynamic: summary
